{
    "nome": "Abu-Zuz",
    "link": "http://guia1.folha.com.br/guia/restaurantes/arabe/11867/abuzuz?sr=1#onde",
    "nota": "Regular",
    "descricao": "Localizado numa rua comercial do Brás, o espaço serve cozinha árabe de ares caseiros com presteza e simplicidade, incluindo pratos menos conhecidos. Disponível às quartas e aos sábados, o uzi de cordeiro é uma massa folhada recheada de arroz e cordeiro desfiado, com coalhada fresca à parte.",
    "preco": "até R$ 60,00",
    "cozinha": "Árabe",
    "endereco": "R. Miller, 622, Brás, Leste, São Paulo, Brasil",
    "endereco_busca": "R. Miller, 622, São Paulo, Brasil",
    "telefone": "3315-9694",
    "localInfo": "Aceita os cartões Amex, Diners, Elo, MasterCard, Visa. Aceita os tíquetes Alelo, Sodexo Pass, Ticket Restaurante Eletrônico. Não aceita cheques. Não faz entrega em domicílio. Aceita reservas. Tem ar-condicionado. Não tem mesas ao ar livre. 60 lugares.",
    "funcionamento": "segunda a sexta: 7h às 17h.sábado: 7h às 15h30.",
    "latlon": [
        -23.5359604,
        -46.6176917
    ]
}