{
    "nome": "Alucci Alucci",
    "link": "http://guia1.folha.com.br/guia/restaurantes/variada/1791761/alucci_alucci?sr=751#onde",
    "nota": "Bom",
    "descricao": "Inspirada no restaurante francês L'Avenue, a casa tem salão classudo, com poltronas vermelhas e banquetas forradas de veludo no bar. Na cozinha, o chef Edson Freire imprime leitura contemporânea aos pratos de inspiração variada, como o robalo grelhado, que chega a mesa ladeado de torta de mandioca recheada de bobó de camarão. De sobremesa, boa pedida é a tapioca com goiabada e sorvete de queijo.",
    "preco": "Acima de R$ 130,00",
    "cozinha": "Variada",
    "endereco": "R. Vitório Fasano, 35, Cerqueira César, Oeste, São Paulo, Brasil",
    "endereco_busca": "R. Vitório Fasano, 35, São Paulo, Brasil",
    "telefone": "3086-1252",
    "localInfo": "Aceita os cartões Amex, Diners, Elo, MasterCard, Visa. Não aceita cheques. Não faz entrega em domicílio. Aceita reservas. Tem ar-condicionado. Não tem mesas ao ar livre. Tem conexão wi-fi. 80 lugares. Valet (R$ 25).",
    "funcionamento": "segunda a sexta: 18h30 às 2h.sábado: a partir das 19h.",
    "latlon": [
        -23.5649368,
        -46.6693678
    ]
}