{
    "nome": "Bazar da Pizza",
    "link": "http://guia1.folha.com.br/guia/restaurantes/pizzarias/710048/bazar_da_pizza?sr=651#onde",
    "nota": false,
    "descricao": "Além de disponibilizar vários rótulos de cerveja, a pizzaria serve sabores como o de alcachofra (molho de tomate, mozarela e fundo de alcachofra) e o largo da Batata (fatias de batata, cobertas com queijo parmesão e alecrim).",
    "preco": "de R$ 60,01 a R$ 75,00",
    "cozinha": "Pizzarias",
    "endereco": "R. Henrique Monteiro, 164, Pinheiros, Oeste, São Paulo, Brasil",
    "endereco_busca": "R. Henrique Monteiro, 164, São Paulo, Brasil",
    "telefone": "3816-6338",
    "localInfo": "Aceita os cartões Amex, Aura, Cabal, Diners, Elo, Good Card, Hipercard, MasterCard, Sorocred, Todos, Visa. Aceita os tíquetes Alelo, Bônus, Sodexo Pass, Ticket Restaurante Eletrônico. Aceita cheques. Faz entrega em domicílio. Aceita reservas. Não tem ar-condicionado. Tem mesas ao ar livre. Tem conexão wi-fi. Possui cadeirões para bebês. 90 lugares.",
    "funcionamento": "segunda: 12h às 15h.terça a sexta: 12h às 15h e 18h30 às 23h.sábado: 18h30 às 23h.",
    "latlon": [
        -23.5694744,
        -46.690199
    ]
}