{
    "nome": "Bibi",
    "link": "http://guia1.folha.com.br/guia/restaurantes/bufequilo/1380316/bibi?sr=101#onde",
    "nota": "Regular",
    "descricao": "A casa de Lia e Marcela Tullman tem fachada discreta e dois ambientes distintos e espaçosos. O sistema é bufê, com preços distintos durante a semana, quando os doces são cobrados à parte, e aos domingos, quando estão inclusos. Entre os pratos, que variam diariamente, há o nhoque de abóbora ao roquefort.",
    "preco": "de R$ 60,01 a R$ 75,00",
    "cozinha": "Bufê/quilo",
    "endereco": "R. Jorge Coelho, 98, Jardim Paulistano, Oeste, São Paulo, Brasil",
    "endereco_busca": "R. Jorge Coelho, 98, São Paulo, Brasil",
    "telefone": "3078-7200",
    "localInfo": "Aceita os cartões Amex, Diners, Elo, Hipercard, MasterCard, Visa. Aceita os tíquetes Alelo, Sodexo Pass, Ticket Restaurante Eletrônico. Aceita reservas. Tem ar-condicionado. Tem acesso para deficiente. Tem conexão wi-fi. Possui cadeirões para bebês. 160 lugares. Valet (R$ 20).",
    "funcionamento": "segunda a sexta: 12h às 15h.domingo: 12h às 16h.",
    "latlon": [
        -23.5828977,
        -46.6840496
    ]
}