{
    "nome": "Cantina do Mário",
    "link": "http://guia1.folha.com.br/guia/restaurantes/italiana/1491056/cantina_do_mario?sr=301#onde",
    "nota": false,
    "descricao": "Tradicional na cidade, a cantina existe desde 1945 e conquistou a clientela da redondeza com o ambiente simples, de clima familiar. No almoço de segunda a sexta, a casa trabalha com bufê de saladas e pratos variados. Já à noite, mais de 40 tipos de pizzas aparecem no menu à la carte, ao lado de carnes, massas e guarnições. Destaque para o nhoque com molho de tomate. <br>",
    "preco": "de R$ 75,01 a R$ 95,00",
    "cozinha": "Italiana",
    "endereco": "Pça. Min. Fagundes Almeida, 32, 1º andar, Vila Monumento, Sul, São Paulo, Brasil",
    "endereco_busca": "Pça. Min. Fagundes Almeida, 32, São Paulo, Brasil",
    "telefone": "2063-7094",
    "localInfo": "Aceita os cartões Amex, Diners, Elo, Good Card, MasterCard, Visa. Aceita os tíquetes Alelo, Bônus, Good Vale, Sodexo Pass, Ticket Restaurante Eletrônico. Aceita cheques. Faz entrega em domicílio. Aceita reservas. Tem conexão wi-fi. Possui cadeirões para bebês. 200 lugares. Estac. (R$ 14 p/ 2 h, na r. Paulo Bregaro, 238 - convênio).",
    "funcionamento": "segunda a domingo: 10h às 24h.",
    "latlon": [
        -23.5828484,
        -46.6123425
    ]
}