{
    "nome": "Capim Santo",
    "link": "http://guia1.folha.com.br/guia/restaurantes/brasileira/11925/capim_santo?sr=51#onde",
    "nota": "Bom",
    "descricao": "Em uma casa arejada com quintal, a chef Morena Leite resgata ingredientes brasileiros em suas receitas. O robalo em crosta de ervas e castanhas é servido com ratatouille de chuchu, pupunha, abóbora e tomate. No almoço, trabalha com um caprichado bufê.",
    "preco": "de R$ 95,01 a R$ 130,00",
    "cozinha": "Brasileira",
    "endereco": "Al. Min. Rocha Azevedo, 471, Cerqueira César, Oeste, São Paulo, Brasil",
    "endereco_busca": "Al. Min. Rocha Azevedo, 471, São Paulo, Brasil",
    "telefone": "3089-9500",
    "localInfo": "Aceita os cartões Amex, Diners, Elo, MasterCard, Visa. Aceita cheques. Não faz entrega em domicílio. Aceita reservas. Tem ar-condicionado. Tem acesso para deficiente. Tem mesas ao ar livre. 200 lugares. Valet (R$ 25).",
    "funcionamento": "terça a sexta: 12h às 15h e 19h30 às 24h.sábado: 12h30 às 16h30 e 20h às 24h.domingo: 12h30 às 17h.",
    "latlon": [
        -23.5621882,
        -46.6601581
    ]
}