{
    "nome": "Carbone",
    "link": "http://guia1.folha.com.br/guia/restaurantes/carnes/2291712/carbone?sr=101#onde",
    "nota": "Regular",
    "descricao": "Os cortes bovinos são as vedetes da nova casa do chef Carlos Bertolazzi. Instalada numa esquina da Cerro Corá, trabalha com sistema à la carte para as carnes e rodízio para os acompanhamentos. Dentre as opções, destaque para o bife de chorizo e para a costelinha suína, que vem acompanhada de um potinho com molho barbecue.",
    "preco": "de R$ 95,01 a R$ 130,00",
    "cozinha": "Carnes",
    "endereco": "R. Cerro Corá, 1.556, Vila Romana, Oeste, São Paulo, Brasil",
    "endereco_busca": "R. Cerro Corá, 1.556, São Paulo, Brasil",
    "telefone": "2935-0266",
    "localInfo": "Aceita os cartões Amex, Diners, Elo, Hipercard, MasterCard, Visa. Aceita os tíquetes Alelo, Sodexo Pass, Ticket Restaurante Eletrônico. Aceita cheques. Não faz entrega em domicílio. Aceita reservas. Tem ar-condicionado. Tem acesso para deficiente. Não tem mesas ao ar livre. Tem conexão wi-fi. 120 lugares. Valet (R$ 15).",
    "funcionamento": "terça a sexta: 12h às 15h e 19h às 24h.sábado: 12h às 17h e 19h às 24h.domingo: 12h às 17h.",
    "latlon": [
        -23.5357269,
        -46.7101218
    ]
}