{
    "nome": "Go Fresh",
    "link": "http://guia1.folha.com.br/guia/restaurantes/comidarapida/11841/go_fresh?sr=201#onde",
    "nota": false,
    "descricao": "Dos mesmos donos da rede Wraps, a primeira unidade abriu na praça de alimentação do shopping Center 3. É possível montar a salada com até cinco ingredientes expostos em uma vitrine, molhos e acompanhamentos (grelhados e pães).",
    "preco": "até R$ 60,00",
    "cozinha": "Comida Rápida",
    "endereco": "Av. Rebouças, 3.970, 3º piso, Pinheiros, Oeste, São Paulo, Brasil",
    "endereco_busca": "Av. Rebouças, 3.970, São Paulo, Brasil",
    "telefone": "2197-7935",
    "localInfo": "Aceita os cartões Amex, Diners, MasterCard, Visa. Aceita os tíquetes Alelo, Sodexo Pass. Não aceita cheques. Não faz entrega em domicílio. Tem ar-condicionado. Tem acesso para deficiente. Estac. (R$ 12 p/ 2 h).",
    "funcionamento": "segunda a domingo: 11h30 às 22h30.",
    "latlon": [
        -23.5725661,
        -46.695732
    ]
}