{
    "nome": "Manihi",
    "link": "http://guia1.folha.com.br/guia/restaurantes/japonesa/375958/manihi?sr=501#onde",
    "nota": "Regular",
    "descricao": "No espaço do antigo Pinotage, oferece um rodízio que, embora bem abastecido, resvala em invenções. Entre as quase duas dezenas de itens há sashimis, sushis, ceviches, tempurás e temakis.",
    "preco": "de R$ 60,01 a R$ 75,00",
    "cozinha": "Japonesa",
    "endereco": "R. Apinajés, 1.359, Sumaré, Oeste, São Paulo, Brasil",
    "endereco_busca": "R. Apinajés, 1.359, São Paulo, Brasil",
    "telefone": "3672-4638",
    "localInfo": "Aceita os cartões Amex, Diners, Elo, MasterCard, Visa. Aceita os tíquetes Alelo, Sodexo Pass, Ticket Restaurante Eletrônico. Aceita cheques. Faz entrega em domicílio. Aceita reservas. Tem ar-condicionado. Tem acesso para deficiente. Tem conexão wi-fi. 92 lugares. Valet (R$ 20).",
    "funcionamento": "segunda: 19h às 23h.terça e quarta: 12h às 15h e 19h às 23h30.quinta: 12h às 15h e 19h às 24h.sexta: 12h às 15h e 19h à 0h30.sábado: 13h às 16h e 19h à 0h30.domingo: 13h às 22h.",
    "latlon": [
        -23.5421728,
        -46.6834876
    ]
}