{
    "nome": "Sevillano Bistrô e Tapas",
    "link": "http://guia1.folha.com.br/guia/restaurantes/espanhola/2153859/sevillano_bistro_e_tapas?sr=251#onde",
    "nota": false,
    "descricao": "A casa da chef Claudia Almeida (que já trabalhou com Ferran Adrià) aposta em uma cozinha europeia variada com toques autorais aqui e ali. A Espanha predomina no menu, em pratos como os croquetes de presunto, servidas de entrada, e o polvo com batatas &ndash;cozinhado lentamente em baixas temperaturas. De sobremesa, prove a sopa de chocolate com azeite, farofa doce e sorvete de iogurte.",
    "preco": "de R$ 75,01 a R$ 95,00",
    "cozinha": "Espanhola",
    "endereco": "Al. Lorena, 871, Jardim Paulista, Oeste, São Paulo, Brasil",
    "endereco_busca": "Al. Lorena, 871, São Paulo, Brasil",
    "telefone": "3774-6877",
    "localInfo": "Aceita os cartões Diners, Elo, MasterCard, Visa. Não aceita cheques. Aceita reservas. Tem ar-condicionado. Tem mesas ao ar livre. Tem conexão wi-fi. 42 lugares.",
    "funcionamento": "terça a sexta: 12h às 15h e 19h às 24h.sábado: 12h às 16h e 19h às 24h.domingo: 12h às 17h.",
    "latlon": [
        -23.5680356,
        -46.6614763
    ]
}