{
    "nome": "Soggiorno Pizzeria",
    "link": "http://guia1.folha.com.br/guia/restaurantes/pizzarias/12551/soggiorno_pizzeria?sr=701#onde",
    "nota": "Regular",
    "descricao": "Serve pizzas preparadas com molho de tomates pelados italianos. Entre os sabores, estão a Originale, com mozarela de búfala, brie e presunto Parma, e a de abobrinha grelhada, também com mozarela de búfala mais parmesão.",
    "preco": "de R$ 60,01 a R$ 75,00",
    "cozinha": "Pizzarias",
    "endereco": "R. Cerro Corá, 1.841, Vila Romana, Oeste, São Paulo, Brasil",
    "endereco_busca": "R. Cerro Corá, 1.841, São Paulo, Brasil",
    "telefone": "3022-8783",
    "localInfo": "Aceita os cartões Amex, Diners, Elo, MasterCard, Visa. Não aceita cheques. Faz entrega em domicílio. Aceita reservas. Tem ar-condicionado. Tem acesso para deficiente. Não tem mesas ao ar livre. Tem conexão wi-fi. 100 lugares. Valet (R$ 15).",
    "funcionamento": "terça a quinta e domingo: 18h às 23h30.sexta e sábado: 18h à 0h30.",
    "latlon": [
        -23.5354263,
        -46.712537
    ]
}