{
    "nome": "Taizan",
    "link": "http://guia1.folha.com.br/guia/restaurantes/chinesa/1177303/taizan?sr=201#onde",
    "nota": false,
    "descricao": "Inaugurado na década de 1970, o restaurante tem decoração excêntrica, com mesas redondas, chão forrado por carpete vermelho e um jardim com bambus aos fundos. O cardápio lista pratos clássicos chineses, a exemplo do risoto de camarão, com ovo e legumes, e do frango empanado ao molho de gengibre. As porções, sempre fartas, servem duas pessoas.",
    "preco": "de R$ 95,01 a R$ 130,00",
    "cozinha": "Chinesa",
    "endereco": "R. Galvão Bueno, 544/562, Liberdade, Centro, São Paulo, Brasil",
    "endereco_busca": "R. Galvão Bueno, 544/562, São Paulo, Brasil",
    "telefone": "3277-8550",
    "localInfo": "Aceita os cartões Amex, Diners, MasterCard, Visa. Não aceita cheques. Faz entrega em domicílio. Aceita reservas. Tem ar-condicionado. Tem acesso para deficiente. Não tem mesas ao ar livre. Tem conexão wi-fi. Possui cadeirões para bebês. 168 lugares. Estac. (R$ 10 - convênio).",
    "funcionamento": "terça a sábado: 11h às 23h.domingo: 11h às 22h.",
    "latlon": [
        -23.5604629,
        -46.6349654
    ]
}