{
    "nome": "Tasca do Zé e da Maria",
    "link": "http://guia1.folha.com.br/guia/restaurantes/portuguesa/1167640/tasca_do_ze_e_da_maria?sr=701#onde",
    "nota": "Bom",
    "descricao": "Os donos do restaurante são egressos do extinto Antiquarius. O menu abarca receitas de inspiração portuguesa, a exemplo do bacalhau à lagareiro e da versão à Beneditine, servida como entrada. Há também opções sem o pescado, caso do arroz de pato. Para finalizar, aposte nos docinhos conventuais, feitos de açúcar e ovos. <br>",
    "preco": "Acima de R$ 130,00",
    "cozinha": "Portuguesa",
    "endereco": "R. dos Pinheiros, 434, Pinheiros, Oeste, São Paulo, Brasil",
    "endereco_busca": "R. dos Pinheiros, 434, São Paulo, Brasil",
    "telefone": "3062-5722",
    "localInfo": "Aceita os cartões Amex, Diners, Elo, MasterCard, Visa. Aceita cheques. Não faz entrega em domicílio. Aceita reservas. Tem ar-condicionado. Tem acesso para deficiente. Tem mesas ao ar livre. Tem conexão wi-fi. Possui menu executivo. 42 lugares. Valet (R$ 20).",
    "funcionamento": "segunda a quinta: 12h às 15h e 19h às 23h30.sexta: 12h às 15h e 19h à 0h30.sábado: 12h à 0h30.domingo: 12h às 18h.",
    "latlon": [
        -23.5653843,
        -46.6823187
    ]
}